aaaaaa_pthogen.pth
pth.py
pthogen.py
pthogen-0.2.0.dist-info/LICENSE
pthogen-0.2.0.dist-info/METADATA
pthogen-0.2.0.dist-info/WHEEL
pthogen-0.2.0.dist-info/top_level.txt
pthogen-0.2.0.dist-info/RECORD
