Metadata-Version: 2.1
Name: pthogen
Version: 0.2.0
Summary: Load pthogen entry_points at pth time.
Home-page: https://github.com/graingert/pthogen
Author: Thomas Grainger
Author-email: pthogen@graingert.co.uk
License: UNKNOWN
Platform: UNKNOWN
Classifier: License :: OSI Approved :: MIT License
Classifier: Programming Language :: Python
Classifier: Programming Language :: Python :: 2
Classifier: Programming Language :: Python :: 2.7
Classifier: Programming Language :: Python :: 3
Classifier: Programming Language :: Python :: 3.5
Classifier: Programming Language :: Python :: 3.6
Classifier: Programming Language :: Python :: 3.7
Classifier: Programming Language :: Python :: 3.8
Requires-Dist: importlib-resources ; python_version < "3.7"
